function_tool_derrick/UsualTool.py
function_tool_derrick/__init__.py
function_tool-0.0.4.dist-info/LICENSE
function_tool-0.0.4.dist-info/METADATA
function_tool-0.0.4.dist-info/WHEEL
function_tool-0.0.4.dist-info/top_level.txt
function_tool-0.0.4.dist-info/RECORD
