Metadata-Version: 2.1
Name: function-tool
Version: 0.0.4
Summary: some usual tool with class
Home-page: https://gitee.com/DerrickChiu/function_tool.git
Author: DerrickChiu
Author-email: chiull@foxmail.com
License: MIT
Platform: UNKNOWN
Classifier: Topic :: Scientific/Engineering
Classifier: Topic :: Scientific/Engineering :: GIS
Classifier: Programming Language :: Python
Classifier: Programming Language :: Python :: 3
Classifier: Programming Language :: Python :: 3.6
Classifier: Programming Language :: Python :: 3.7
Classifier: Programming Language :: Python :: 3.8
Classifier: Programming Language :: Python :: 3.9
Classifier: Programming Language :: Python :: 3.10
Classifier: Programming Language :: Python :: 3.11
Classifier: Programming Language :: Python :: 3.12
Classifier: Programming Language :: Python :: Implementation :: CPython
